{
  "version": 1,
  "updatedAt": "2026-05-17T09:00:43.879Z",
  "entries": [
    {
      "linkId": "live-with-the-hive-podcast",
      "label": "Hive Minded YouTube",
      "platform": "live-with-the-hive-podcast",
      "handle": "hiveminded21",
      "canonicalUrl": "https://www.youtube.com/@HiveMinded21",
      "audienceKind": "subscribers",
      "csvPath": "history/followers/live-with-the-hive-podcast.csv",
      "latestAudienceCount": 266,
      "latestAudienceCountRaw": "266 subscribers",
      "latestObservedAt": "2026-05-17T09:00:43.879Z"
    },
    {
      "linkId": "rumble",
      "label": "RUMBLE",
      "platform": "rumble",
      "handle": "c-7752998",
      "canonicalUrl": "https://rumble.com/c/c-7752998",
      "audienceKind": "followers",
      "csvPath": "history/followers/rumble.csv",
      "latestAudienceCount": 23,
      "latestAudienceCountRaw": "23 Followers",
      "latestObservedAt": "2026-05-17T09:00:43.879Z"
    },
    {
      "linkId": "the-bitcoin-nova-x",
      "label": "The Bitcoin Nova X",
      "platform": "x",
      "handle": "thebitcoinnova",
      "canonicalUrl": "https://x.com/TheBitcoinNova",
      "audienceKind": "followers",
      "csvPath": "history/followers/the-bitcoin-nova-x.csv",
      "latestAudienceCount": 494,
      "latestAudienceCountRaw": "494 Followers",
      "latestObservedAt": "2026-05-17T09:00:43.879Z"
    },
    {
      "linkId": "x",
      "label": "X",
      "platform": "x",
      "handle": "stacinova",
      "canonicalUrl": "https://x.com/StaciNova",
      "audienceKind": "followers",
      "csvPath": "history/followers/x.csv",
      "latestAudienceCount": 5665,
      "latestAudienceCountRaw": "5,665 Followers",
      "latestObservedAt": "2026-05-17T09:00:43.879Z"
    },
    {
      "linkId": "youtube",
      "label": "Staci Nova YouTube",
      "platform": "youtube",
      "handle": "stacinova",
      "canonicalUrl": "https://www.youtube.com/@StaciNova",
      "audienceKind": "subscribers",
      "csvPath": "history/followers/youtube.csv",
      "latestAudienceCount": 12000,
      "latestAudienceCountRaw": "12K subscribers",
      "latestObservedAt": "2026-05-17T09:00:43.879Z"
    }
  ]
}
